setup.cfg
setup.py
matches/__init__.py
matches.egg-info/PKG-INFO
matches.egg-info/SOURCES.txt
matches.egg-info/dependency_links.txt
matches.egg-info/not-zip-safe
matches.egg-info/top_level.txt