Metadata-Version: 1.1
Name: matches
Version: 0.0.1
Summary: A little bit of Pattern matching for Python
Home-page: http://github.com/clarete/matches
Author: Lincoln Clarete
Author-email: lincoln@clarete.li
License: MIT
Platform: UNKNOWN
Classifier: License :: OSI Approved :: MIT License
